{"assets":[{"id":"4LnY7hrfCivD3LiqiUPTh","layers":[{"ddd":0,"ind":2,"ty":4,"ln":"layer_2","sr":1,"ks":{"a":{"a":0,"k":[50.5,6]},"o":{"a":1,"k":[{"t":0,"s":[0],"i":{"x":0,"y":0},"o":{"x":1,"y":1}},{"t":1,"s":[4.21],"i":{"x":0,"y":0},"o":{"x":1,"y":1}},{"t":2,"s":[8.41],"i":{"x":0,"y":0},"o":{"x":1,"y":1}},{"t":3,"s":[12.62],"i":{"x":0,"y":0},"o":{"x":1,"y":1}},{"t":4,"s":[16.83],"i":{"x":0,"y":0},"o":{"x":1,"y":1}},{"t":5,"s":[21.03],"i":{"x":0,"y":0},"o":{"x":1,"y":1}},{"t":6,"s":[25.24],"i":{"x":0,"y":0},"o":{"x":1,"y":1}},{"t":7,"s":[29.45],"i":{"x":0,"y":0},"o":{"x":1,"y":1}},{"t":8,"s":[33.65],"i":{"x":0,"y":0},"o":{"x":1,"y":1}},{"t":9,"s":[37.86],"i":{"x":0,"y":0},"o":{"x":1,"y":1}},{"t":10,"s":[42.07],"i":{"x":0,"y":0},"o":{"x":1,"y":1}},{"t":11,"s":[46.27],"i":{"x":0,"y":0},"o":{"x":1,"y":1}},{"t":12,"s":[50.48],"i":{"x":0,"y":0},"o":{"x":1,"y":1}},{"t":13,"s":[54.69],"i":{"x":0,"y":0},"o":{"x":1,"y":1}},{"t":14,"s":[58.89],"i":{"x":0,"y":0},"o":{"x":1,"y":1}},{"t":15,"s":[63.1],"i":{"x":0,"y":0},"o":{"x":1,"y":1}},{"t":16,"s":[67.3],"i":{"x":0,"y":0},"o":{"x":1,"y":1}},{"t":17,"s":[71.51],"i":{"x":0,"y":0},"o":{"x":1,"y":1}},{"t":18,"s":[75.72],"i":{"x":0,"y":0},"o":{"x":1,"y":1}},{"t":19,"s":[79.92],"i":{"x":0,"y":0},"o":{"x":1,"y":1}},{"t":20,"s":[84.13],"i":{"x":0,"y":0},"o":{"x":1,"y":1}},{"t":21,"s":[88.34],"i":{"x":0,"y":0},"o":{"x":1,"y":1}},{"t":22,"s":[92.54],"i":{"x":0,"y":0},"o":{"x":1,"y":1}},{"t":23,"s":[96.75],"i":{"x":0,"y":0},"o":{"x":1,"y":1}},{"t":24,"s":[100],"i":{"x":0,"y":0},"o":{"x":1,"y":1}}]},"p":{"a":0,"k":[267.5,299]},"r":{"a":0,"k":0},"s":{"a":0,"k":[100,91.67]},"sk":{"a":0,"k":0},"sa":{"a":0,"k":0}},"ao":0,"ip":0,"op":103,"st":0,"bm":0,"shapes":[{"ty":"gr","nm":"surface131","it":[{"ty":"gr","it":[{"ty":"sh","d":1,"ks":{"a":0,"k":{"c":true,"i":[[0,0],[0,-0.41],[-0.42,0]],"o":[[-0.42,0],[0,0.41],[0,0]],"v":[[1.5,5.25],[0.75,6],[1.5,6.75]]}}},{"ty":"sh","d":1,"ks":{"a":0,"k":{"c":true,"i":[[0,0],[0.29,0.29],[0,0],[0.29,-0.29],[-0.29,-0.29],[0,0],[0,0],[-0.29,-0.29],[-0.29,0.29]],"o":[[0.29,-0.29],[0,0],[-0.29,-0.29],[-0.29,0.29],[0,0],[0,0],[-0.29,0.29],[0.29,0.29],[0,0]],"v":[[99.54,6.53],[99.54,5.47],[94.76,0.7],[93.7,0.7],[93.7,1.76],[97.95,6],[93.7,10.24],[93.7,11.3],[94.76,11.3]]}}},{"ty":"sh","d":1,"ks":{"a":0,"k":{"c":true,"i":[[0,0],[0,0],[0,0],[0,0]],"o":[[0,0],[0,0],[0,0],[0,0]],"v":[[1.5,6.75],[99.01,6.75],[99.01,5.25],[1.5,5.25]]}}},{"ty":"fl","c":{"a":0,"k":[0.78,0.78,0.78,1]},"r":1,"o":{"a":0,"k":80}},{"ty":"tr","nm":"Transform","a":{"a":0,"k":[0,0]},"o":{"a":0,"k":100},"p":{"a":0,"k":[0,0]},"r":{"a":0,"k":0},"s":{"a":0,"k":[100,100]},"sk":{"a":0,"k":0},"sa":{"a":0,"k":0}}]},{"ty":"tr","nm":"Transform","a":{"a":0,"k":[0,0]},"o":{"a":0,"k":100},"p":{"a":0,"k":[0,0]},"r":{"a":0,"k":0},"s":{"a":0,"k":[100,100]},"sk":{"a":0,"k":0},"sa":{"a":0,"k":0}}]}]},{"ddd":0,"ind":3,"ty":4,"ln":"layer_3","sr":1,"ks":{"a":{"a":0,"k":[50,6]},"o":{"a":1,"k":[{"t":0,"s":[0],"i":{"x":0,"y":0},"o":{"x":1,"y":1}},{"t":51,"s":[0],"i":{"x":0,"y":0},"o":{"x":1,"y":1}},{"t":52,"s":[1.86],"i":{"x":0,"y":0},"o":{"x":1,"y":1}},{"t":53,"s":[6.07],"i":{"x":0,"y":0},"o":{"x":1,"y":1}},{"t":54,"s":[10.28],"i":{"x":0,"y":0},"o":{"x":1,"y":1}},{"t":55,"s":[14.48],"i":{"x":0,"y":0},"o":{"x":1,"y":1}},{"t":56,"s":[18.69],"i":{"x":0,"y":0},"o":{"x":1,"y":1}},{"t":57,"s":[22.9],"i":{"x":0,"y":0},"o":{"x":1,"y":1}},{"t":58,"s":[27.1],"i":{"x":0,"y":0},"o":{"x":1,"y":1}},{"t":59,"s":[31.31],"i":{"x":0,"y":0},"o":{"x":1,"y":1}},{"t":60,"s":[35.52],"i":{"x":0,"y":0},"o":{"x":1,"y":1}},{"t":61,"s":[39.72],"i":{"x":0,"y":0},"o":{"x":1,"y":1}},{"t":62,"s":[43.93],"i":{"x":0,"y":0},"o":{"x":1,"y":1}},{"t":63,"s":[48.14],"i":{"x":0,"y":0},"o":{"x":1,"y":1}},{"t":64,"s":[52.34],"i":{"x":0,"y":0},"o":{"x":1,"y":1}},{"t":65,"s":[56.55],"i":{"x":0,"y":0},"o":{"x":1,"y":1}},{"t":66,"s":[60.76],"i":{"x":0,"y":0},"o":{"x":1,"y":1}},{"t":67,"s":[64.96],"i":{"x":0,"y":0},"o":{"x":1,"y":1}},{"t":68,"s":[69.17],"i":{"x":0,"y":0},"o":{"x":1,"y":1}},{"t":69,"s":[73.38],"i":{"x":0,"y":0},"o":{"x":1,"y":1}},{"t":70,"s":[77.58],"i":{"x":0,"y":0},"o":{"x":1,"y":1}},{"t":71,"s":[81.79],"i":{"x":0,"y":0},"o":{"x":1,"y":1}},{"t":72,"s":[85.99],"i":{"x":0,"y":0},"o":{"x":1,"y":1}},{"t":73,"s":[90.2],"i":{"x":0,"y":0},"o":{"x":1,"y":1}},{"t":74,"s":[94.41],"i":{"x":0,"y":0},"o":{"x":1,"y":1}},{"t":75,"s":[98.61],"i":{"x":0,"y":0},"o":{"x":1,"y":1}},{"t":76,"s":[100],"i":{"x":0,"y":0},"o":{"x":1,"y":1}}]},"p":{"a":0,"k":[268,234]},"r":{"a":0,"k":0},"s":{"a":0,"k":[102,91.67]},"sk":{"a":0,"k":0},"sa":{"a":0,"k":0}},"ao":0,"ip":0,"op":103,"st":0,"bm":0,"shapes":[{"ty":"gr","nm":"surface136","it":[{"ty":"gr","it":[{"ty":"sh","d":1,"ks":{"a":0,"k":{"c":true,"i":[[0,0],[0,0.41],[0.41,0]],"o":[[0.41,0],[0,-0.41],[0,0]],"v":[[98.26,6.75],[99.01,6],[98.26,5.25]]}}},{"ty":"sh","d":1,"ks":{"a":0,"k":{"c":true,"i":[[0,0],[-0.29,-0.29],[0,0],[-0.29,0.29],[0.29,0.29],[0,0],[0,0],[0.29,0.29],[0.29,-0.29]],"o":[[-0.29,0.29],[0,0],[0.29,0.29],[0.29,-0.29],[0,0],[0,0],[0.29,-0.29],[-0.29,-0.29],[0,0]],"v":[[0.22,5.47],[0.22,6.53],[4.99,11.3],[6.05,11.3],[6.05,10.24],[1.81,6],[6.05,1.76],[6.05,0.7],[4.99,0.7]]}}},{"ty":"sh","d":1,"ks":{"a":0,"k":{"c":true,"i":[[0,0],[0,0],[0,0],[0,0]],"o":[[0,0],[0,0],[0,0],[0,0]],"v":[[98.26,5.25],[0.75,5.25],[0.75,6.75],[98.26,6.75]]}}},{"ty":"fl","c":{"a":0,"k":[0.78,0.78,0.78,1]},"r":1,"o":{"a":0,"k":100}},{"ty":"tr","nm":"Transform","a":{"a":0,"k":[0,0]},"o":{"a":0,"k":100},"p":{"a":0,"k":[0,0]},"r":{"a":0,"k":0},"s":{"a":0,"k":[100,100]},"sk":{"a":0,"k":0},"sa":{"a":0,"k":0}}]},{"ty":"tr","nm":"Transform","a":{"a":0,"k":[0,0]},"o":{"a":0,"k":100},"p":{"a":0,"k":[0,0]},"r":{"a":0,"k":0},"s":{"a":0,"k":[100,100]},"sk":{"a":0,"k":0},"sa":{"a":0,"k":0}}]}]},{"ddd":0,"ind":4,"ty":4,"ln":"layer_4","sr":1,"ks":{"a":{"a":0,"k":[6,27]},"o":{"a":1,"k":[{"t":0,"s":[0],"i":{"x":0,"y":0},"o":{"x":1,"y":1}},{"t":77,"s":[0],"i":{"x":0,"y":0},"o":{"x":1,"y":1}},{"t":78,"s":[3.17],"i":{"x":0,"y":0},"o":{"x":1,"y":1}},{"t":79,"s":[7.38],"i":{"x":0,"y":0},"o":{"x":1,"y":1}},{"t":80,"s":[11.59],"i":{"x":0,"y":0},"o":{"x":1,"y":1}},{"t":81,"s":[15.79],"i":{"x":0,"y":0},"o":{"x":1,"y":1}},{"t":82,"s":[20],"i":{"x":0,"y":0},"o":{"x":1,"y":1}},{"t":83,"s":[24.21],"i":{"x":0,"y":0},"o":{"x":1,"y":1}},{"t":84,"s":[28.41],"i":{"x":0,"y":0},"o":{"x":1,"y":1}},{"t":85,"s":[32.62],"i":{"x":0,"y":0},"o":{"x":1,"y":1}},{"t":86,"s":[36.83],"i":{"x":0,"y":0},"o":{"x":1,"y":1}},{"t":87,"s":[41.03],"i":{"x":0,"y":0},"o":{"x":1,"y":1}},{"t":88,"s":[45.24],"i":{"x":0,"y":0},"o":{"x":1,"y":1}},{"t":89,"s":[49.45],"i":{"x":0,"y":0},"o":{"x":1,"y":1}},{"t":90,"s":[53.65],"i":{"x":0,"y":0},"o":{"x":1,"y":1}},{"t":91,"s":[57.86],"i":{"x":0,"y":0},"o":{"x":1,"y":1}},{"t":92,"s":[62.07],"i":{"x":0,"y":0},"o":{"x":1,"y":1}},{"t":93,"s":[66.27],"i":{"x":0,"y":0},"o":{"x":1,"y":1}},{"t":94,"s":[70.48],"i":{"x":0,"y":0},"o":{"x":1,"y":1}},{"t":95,"s":[74.69],"i":{"x":0,"y":0},"o":{"x":1,"y":1}},{"t":96,"s":[78.89],"i":{"x":0,"y":0},"o":{"x":1,"y":1}},{"t":97,"s":[83.1],"i":{"x":0,"y":0},"o":{"x":1,"y":1}},{"t":98,"s":[87.3],"i":{"x":0,"y":0},"o":{"x":1,"y":1}},{"t":99,"s":[91.51],"i":{"x":0,"y":0},"o":{"x":1,"y":1}},{"t":100,"s":[95.72],"i":{"x":0,"y":0},"o":{"x":1,"y":1}},{"t":101,"s":[99.92],"i":{"x":0,"y":0},"o":{"x":1,"y":1}},{"t":102,"s":[100],"i":{"x":0,"y":0},"o":{"x":1,"y":1}}]},"p":{"a":0,"k":[207.99,265.5]},"r":{"a":0,"k":0},"s":{"a":0,"k":[116.67,116.67]},"sk":{"a":0,"k":0},"sa":{"a":0,"k":0}},"ao":0,"ip":0,"op":103,"st":0,"bm":0,"shapes":[{"ty":"gr","nm":"surface141","it":[{"ty":"gr","it":[{"ty":"sh","d":1,"ks":{"a":0,"k":{"c":true,"i":[[0,0],[0.41,0],[0,-0.41]],"o":[[0,-0.41],[-0.41,0],[0,0]],"v":[[6.75,0.75],[6,0],[5.25,0.75]]}}},{"ty":"sh","d":1,"ks":{"a":0,"k":{"c":true,"i":[[0,0],[-0.29,0.29],[0,0],[0.29,0.29],[0.29,-0.29],[0,0],[0,0],[0.29,-0.29],[-0.29,-0.29]],"o":[[0.29,0.29],[0,0],[0.29,-0.29],[-0.29,-0.29],[0,0],[0,0],[-0.29,-0.29],[-0.29,0.29],[0,0]],"v":[[5.47,53.78],[6.53,53.78],[11.3,49.01],[11.3,47.95],[10.24,47.95],[6,52.19],[1.76,47.95],[0.7,47.95],[0.7,49.01]]}}},{"ty":"sh","d":1,"ks":{"a":0,"k":{"c":true,"i":[[0,0],[0,0],[0,0],[0,0]],"o":[[0,0],[0,0],[0,0],[0,0]],"v":[[5.25,0.75],[5.25,53.25],[6.75,53.25],[6.75,0.75]]}}},{"ty":"fl","c":{"a":0,"k":[0.78,0.78,0.78,1]},"r":1,"o":{"a":0,"k":100}},{"ty":"tr","nm":"Transform","a":{"a":0,"k":[0,0]},"o":{"a":0,"k":100},"p":{"a":0,"k":[0,0]},"r":{"a":0,"k":0},"s":{"a":0,"k":[100,100]},"sk":{"a":0,"k":0},"sa":{"a":0,"k":0}}]},{"ty":"tr","nm":"Transform","a":{"a":0,"k":[0,0]},"o":{"a":0,"k":100},"p":{"a":0,"k":[0,0]},"r":{"a":0,"k":0},"s":{"a":0,"k":[100,100]},"sk":{"a":0,"k":0},"sa":{"a":0,"k":0}}]}]},{"ddd":0,"ind":5,"ty":4,"ln":"layer_5","sr":1,"ks":{"a":{"a":0,"k":[6,27]},"o":{"a":1,"k":[{"t":0,"s":[0],"i":{"x":0,"y":0},"o":{"x":1,"y":1}},{"t":26,"s":[0],"i":{"x":0,"y":0},"o":{"x":1,"y":1}},{"t":27,"s":[3.5],"i":{"x":0,"y":0},"o":{"x":1,"y":1}},{"t":28,"s":[7.71],"i":{"x":0,"y":0},"o":{"x":1,"y":1}},{"t":29,"s":[11.91],"i":{"x":0,"y":0},"o":{"x":1,"y":1}},{"t":30,"s":[16.12],"i":{"x":0,"y":0},"o":{"x":1,"y":1}},{"t":31,"s":[20.33],"i":{"x":0,"y":0},"o":{"x":1,"y":1}},{"t":32,"s":[24.53],"i":{"x":0,"y":0},"o":{"x":1,"y":1}},{"t":33,"s":[28.74],"i":{"x":0,"y":0},"o":{"x":1,"y":1}},{"t":34,"s":[32.95],"i":{"x":0,"y":0},"o":{"x":1,"y":1}},{"t":35,"s":[37.15],"i":{"x":0,"y":0},"o":{"x":1,"y":1}},{"t":36,"s":[41.36],"i":{"x":0,"y":0},"o":{"x":1,"y":1}},{"t":37,"s":[45.57],"i":{"x":0,"y":0},"o":{"x":1,"y":1}},{"t":38,"s":[49.77],"i":{"x":0,"y":0},"o":{"x":1,"y":1}},{"t":39,"s":[53.98],"i":{"x":0,"y":0},"o":{"x":1,"y":1}},{"t":40,"s":[58.19],"i":{"x":0,"y":0},"o":{"x":1,"y":1}},{"t":41,"s":[62.39],"i":{"x":0,"y":0},"o":{"x":1,"y":1}},{"t":42,"s":[66.6],"i":{"x":0,"y":0},"o":{"x":1,"y":1}},{"t":43,"s":[70.81],"i":{"x":0,"y":0},"o":{"x":1,"y":1}},{"t":44,"s":[75.01],"i":{"x":0,"y":0},"o":{"x":1,"y":1}},{"t":45,"s":[79.22],"i":{"x":0,"y":0},"o":{"x":1,"y":1}},{"t":46,"s":[83.43],"i":{"x":0,"y":0},"o":{"x":1,"y":1}},{"t":47,"s":[87.63],"i":{"x":0,"y":0},"o":{"x":1,"y":1}},{"t":48,"s":[91.84],"i":{"x":0,"y":0},"o":{"x":1,"y":1}},{"t":49,"s":[96.05],"i":{"x":0,"y":0},"o":{"x":1,"y":1}},{"t":50,"s":[100],"i":{"x":0,"y":0},"o":{"x":1,"y":1}}]},"p":{"a":0,"k":[325.5,265.5]},"r":{"a":0,"k":0},"s":{"a":0,"k":[108.33,116.67]},"sk":{"a":0,"k":0},"sa":{"a":0,"k":0}},"ao":0,"ip":0,"op":103,"st":0,"bm":0,"shapes":[{"ty":"gr","nm":"surface146","it":[{"ty":"gr","it":[{"ty":"sh","d":1,"ks":{"a":0,"k":{"c":true,"i":[[0,0],[-0.41,0],[0,0.41]],"o":[[0.01,0.41],[0.41,-0.01],[0,0]],"v":[[6,53.25],[6.76,54],[7.5,53.23]]}}},{"ty":"sh","d":1,"ks":{"a":0,"k":{"c":true,"i":[[0,0],[0.29,-0.3],[0,0],[-0.3,-0.29],[-0.29,0.3],[0,0],[0,0],[-0.29,0.3],[0.3,0.29]],"o":[[-0.3,-0.29],[0,0],[-0.29,0.3],[0.3,0.29],[0,0],[0,0],[0.3,0.29],[0.29,-0.3],[0,0]],"v":[[6.52,0.21],[5.46,0.23],[0.76,5.07],[0.77,6.13],[1.83,6.11],[6.02,1.81],[10.32,5.99],[11.38,5.98],[11.36,4.92]]}}},{"ty":"sh","d":1,"ks":{"a":0,"k":{"c":true,"i":[[0,0],[0,0],[0,0],[0,0]],"o":[[0,0],[0,0],[0,0],[0,0]],"v":[[7.5,53.23],[6.75,0.74],[5.25,0.76],[6,53.25]]}}},{"ty":"fl","c":{"a":0,"k":[0.78,0.78,0.78,1]},"r":1,"o":{"a":0,"k":100}},{"ty":"tr","nm":"Transform","a":{"a":0,"k":[0,0]},"o":{"a":0,"k":100},"p":{"a":0,"k":[0,0]},"r":{"a":0,"k":0},"s":{"a":0,"k":[100,100]},"sk":{"a":0,"k":0},"sa":{"a":0,"k":0}}]},{"ty":"tr","nm":"Transform","a":{"a":0,"k":[0,0]},"o":{"a":0,"k":100},"p":{"a":0,"k":[0,0]},"r":{"a":0,"k":0},"s":{"a":0,"k":[100,100]},"sk":{"a":0,"k":0},"sa":{"a":0,"k":0}}]}]},{"ddd":0,"ind":6,"ty":4,"ln":"layer_6","sr":1,"ks":{"a":{"a":0,"k":[47.5,24.5]},"o":{"a":0,"k":100},"p":{"a":0,"k":[267.49,267.5]},"r":{"a":0,"k":0},"s":{"a":0,"k":[114.74,114.29]},"sk":{"a":0,"k":0},"sa":{"a":0,"k":0}},"ao":0,"ip":0,"op":103,"st":0,"bm":0,"shapes":[{"ty":"gr","nm":"surface151","it":[{"ty":"gr","it":[{"ty":"gr","it":[{"ty":"sh","d":1,"ks":{"a":0,"k":{"c":true,"i":[[0,0],[25.32,0],[0.84,-0.92],[-0.89,-0.97],[-25.32,0],[-0.84,0.92],[0.89,0.98]],"o":[[-0.84,-0.92],[-25.32,0],[-0.89,0.98],[0.84,0.92],[25.32,0],[0.89,-0.97],[0,0]],"v":[[93.16,22.58],[46.91,0],[0.67,22.58],[0.67,26.05],[46.91,48.63],[93.16,26.05],[93.16,22.58]]}}},{"ty":"sh","d":1,"ks":{"a":0,"k":{"c":true,"i":[[0,0],[5.24,5.03],[-19.16,0],[-5.24,-5.03],[18.71,-1.12]],"o":[[-19.54,-1.12],[5.24,-5.03],[19.16,0],[-5.24,5.03],[0,0]],"v":[[46.91,44.4],[6,24.32],[46.91,4.28],[87.83,24.32],[46.91,44.4]]}}},{"ty":"fl","c":{"a":0,"k":[0.13,0.13,0.13,1]},"r":1,"o":{"a":0,"k":100}},{"ty":"tr","nm":"Transform","a":{"a":0,"k":[0,0]},"o":{"a":0,"k":100},"p":{"a":0,"k":[0,0]},"r":{"a":0,"k":0},"s":{"a":0,"k":[100,100]},"sk":{"a":0,"k":0},"sa":{"a":0,"k":0}}]},{"ty":"tr","nm":"Transform","a":{"a":0,"k":[0,0]},"o":{"a":0,"k":100},"p":{"a":0,"k":[0,0]},"r":{"a":0,"k":0},"s":{"a":0,"k":[100,100]},"sk":{"a":0,"k":0},"sa":{"a":0,"k":0}}]},{"ty":"tr","nm":"Transform","a":{"a":0,"k":[0,0]},"o":{"a":0,"k":100},"p":{"a":0,"k":[0,0]},"r":{"a":0,"k":0},"s":{"a":0,"k":[100,100]},"sk":{"a":0,"k":0},"sa":{"a":0,"k":0}}]}]},{"ddd":0,"ind":7,"ty":4,"nm":"","ln":"1:4","sr":1,"ks":{"a":{"a":0,"k":[0,0]},"o":{"a":0,"k":100},"p":{"a":0,"k":[266.99,267.5]},"r":{"a":0,"k":0},"s":{"a":0,"k":[100,100]},"sk":{"a":0,"k":0},"sa":{"a":0,"k":0}},"ao":0,"ip":0,"op":103,"st":0,"bm":0,"shapes":[{"ty":"gr","hd":false,"bm":0,"it":[{"ty":"el","hd":false,"p":{"a":0,"k":[0,0]},"s":{"a":0,"k":[13,13]},"d":1},{"ty":"fl","hd":false,"bm":0,"c":{"a":0,"k":[0.27,0.23,0.27]},"r":1,"o":{"a":0,"k":100}},{"ty":"tr","nm":"Transform","a":{"a":0,"k":[0,0]},"o":{"a":0,"k":100},"p":{"a":0,"k":[0,0]},"r":{"a":0,"k":0},"s":{"a":0,"k":[100,100]},"sk":{"a":0,"k":0},"sa":{"a":0,"k":0}}],"np":0}]},{"ddd":0,"ind":8,"ty":4,"ln":"layer_8","sr":1,"ks":{"a":{"a":0,"k":[17.5,18.5]},"o":{"a":0,"k":100},"p":{"a":0,"k":[266.99,267.5]},"r":{"a":0,"k":0},"s":{"a":0,"k":[100,97.3]},"sk":{"a":0,"k":0},"sa":{"a":0,"k":0}},"ao":0,"ip":0,"op":103,"st":0,"bm":0,"shapes":[{"ty":"gr","nm":"surface156","it":[{"ty":"gr","nm":"use","it":[{"ty":"gr","nm":"surface163","it":[{"ty":"gr","it":[{"ty":"gr","it":[{"ty":"sh","d":1,"ks":{"a":0,"k":{"c":true,"i":[[0,0],[-12.96,0],[0,13.31],[12.96,0],[0,-13.31]],"o":[[0,13.31],[12.96,0],[0,-13.31],[-12.96,0],[0,0]],"v":[[0,24.35],[23.5,48.48],[47,24.35],[23.5,0.21],[0,24.35]]}}},{"ty":"st","bm":0,"c":{"a":0,"k":[0.13,0.13,0.13,1]},"lc":1,"lj":1,"ml":4,"o":{"a":0,"k":100},"w":{"a":0,"k":6}},{"ty":"fl","c":{"a":0,"k":[0.64,0.42,0.36,1]},"r":1,"o":{"a":0,"k":100}},{"ty":"tr","nm":"Transform","a":{"a":0,"k":[0,0]},"o":{"a":0,"k":100},"p":{"a":0,"k":[0,0]},"r":{"a":0,"k":0},"s":{"a":0,"k":[75,75]},"sk":{"a":0,"k":0},"sa":{"a":0,"k":0}}]},{"ty":"tr","nm":"Transform","a":{"a":0,"k":[0,0]},"o":{"a":0,"k":100},"p":{"a":0,"k":[0,0]},"r":{"a":0,"k":0},"s":{"a":0,"k":[100,100]},"sk":{"a":0,"k":0},"sa":{"a":0,"k":0}}]},{"ty":"tr","nm":"Transform","a":{"a":0,"k":[0,0]},"o":{"a":0,"k":100},"p":{"a":0,"k":[0,0]},"r":{"a":0,"k":0},"s":{"a":0,"k":[100,100]},"sk":{"a":0,"k":0},"sa":{"a":0,"k":0}}]},{"ty":"tr","nm":"Transform","a":{"a":0,"k":[0,0]},"o":{"a":0,"k":100},"p":{"a":0,"k":[0,0]},"r":{"a":0,"k":0},"s":{"a":0,"k":[100,100]},"sk":{"a":0,"k":0},"sa":{"a":0,"k":0}}]},{"ty":"tr","nm":"Transform","a":{"a":0,"k":[0,0]},"o":{"a":0,"k":100},"p":{"a":0,"k":[0,0]},"r":{"a":0,"k":0},"s":{"a":0,"k":[100,100]},"sk":{"a":0,"k":0},"sa":{"a":0,"k":0}}]}]}]}],"ddd":0,"fr":60,"h":79,"ip":0,"layers":[{"ddd":0,"ind":1,"ty":0,"nm":"","ln":"precomp_1:101","sr":1,"ks":{"a":{"a":0,"k":[268,268]},"o":{"a":0,"k":100},"p":{"a":0,"k":[67.01,39.5]},"r":{"a":0,"k":0},"s":{"a":0,"k":[100,100]},"sk":{"a":0,"k":0},"sa":{"a":0,"k":0}},"ao":0,"w":536,"h":536,"ip":0,"op":103,"st":0,"bm":0,"refId":"4LnY7hrfCivD3LiqiUPTh"}],"meta":{"g":"https://jitter.video"},"nm":"Untitled:-Group-1","op":103,"v":"5.7.4","w":134}